[
{
"kids":[],
"uid":"2810667590",
"parent":"",
"text":"",
"mid":"zv43hCG0f",
"date":"2013-05-04 01:00:01"
},
{
"kids":[],
"uid":"2920633482",
"parent":"",
"text":"",
"mid":"zv43hCFWW",
"date":"2013-05-04 00:59:57"
},
{
"kids":[],
"uid":"2920189930",
"parent":"zqSQoip3M",
"text":"",
"mid":"zuKVM3bqg",
"date":"2013-05-02 00:19:19"
},
{
"kids":[],
"uid":"1582594941",
"parent":"zqSQoip3M",
"text":"",
"mid":"zth15nxxm",
"date":"2013-04-22 06:19:41"
},
{
"kids":[],
"uid":"3043716750",
"parent":"zqSQoip3M",
"text":"",
"mid":"zt73B9eNP",
"date":"2013-04-21 04:58:24"
},
{
"kids":[],
"uid":"3044020490",
"parent":"zqSQoip3M",
"text":"",
"mid":"zsl8drA2R",
"date":"2013-04-16 02:57:56"
},
{
"kids":[],
"uid":"3044281644",
"parent":"zqSQoip3M",
"text":"",
"mid":"zsjiHpmIF",
"date":"2013-04-15 22:18:13"
},
{
"kids":[],
"uid":"2805117472",
"parent":"zqSQoip3M",
"text":"",
"mid":"zsjiH80ZR",
"date":"2013-04-15 22:18:12"
},
{
"kids":[],
"uid":"3043516694",
"parent":"zqRpEgP9U",
"text":"",
"mid":"zs1okyjve",
"date":"2013-04-14 00:42:43"
},
{
"kids":[],
"uid":"2920173574",
"parent":"zqRpEgP9U",
"text":"",
"mid":"zrWOB2pu8",
"date":"2013-04-13 13:03:40"
},
{
"kids":[],
"uid":"2919637880",
"parent":"zqRpEgP9U",
"text":"",
"mid":"zrWOB2prX",
"date":"2013-04-13 13:03:40"
},
{
"kids":[],
"uid":"2919314214",
"parent":"",
"text":"",
"mid":"zrUHtaWX3",
"date":"2013-04-13 07:40:37"
},
{
"kids":[],
"uid":"2863060552",
"parent":"",
"text":"cao，刚开始玩就要收费，cao。",
"mid":"zrORcdsXT",
"date":"2013-04-12 16:48:04"
},
{
"kids":[],
"uid":"2919419410",
"parent":"",
"text":"",
"mid":"zrK4b9t4T",
"date":"2013-04-12 04:36:21"
},
{
"kids":[],
"uid":"2790031852",
"parent":"",
"text":"",
"mid":"zrK4axPnR",
"date":"2013-04-12 04:36:20"
},
{
"kids":[],
"uid":"2919922800",
"parent":"zqTmzsYuN",
"text":"",
"mid":"zrEPCqrOX",
"date":"2013-04-11 15:16:42"
},
{
"kids":[],
"uid":"2805358580",
"parent":"zqTmzsYuN",
"text":"",
"mid":"zrEPC8QEh",
"date":"2013-04-11 15:16:43"
},
{
"kids":[],
"uid":"2670810517",
"parent":"zqSjI7Arx",
"text":"[怒][怒]@lara_lie @Lion聂晨 @不要再发癫的林欣欣 @啊波为yoga君代言 @我是邓珺不要再写成邓郡 @苏厼盈 @",
"mid":"zrDcn1cyV",
"date":"2013-04-11 11:07:18"
},
{
"kids":[],
"uid":"2809252570",
"parent":"zqRo6dvw6",
"text":"",
"mid":"zrqVSwoX4",
"date":"2013-04-10 03:53:43"
},
{
"kids":[],
"uid":"3103293943",
"parent":"zqRDUkxEo",
"text":"",
"mid":"zrmTKvZaU",
"date":"2013-04-09 17:37:27"
},
{
"kids":[],
"uid":"2809636842",
"parent":"zqSQoip3M",
"text":"",
"mid":"zriaisqtX",
"date":"2013-04-09 05:34:31"
},
{
"kids":[],
"uid":"2919684930",
"parent":"zqRqhx8C1",
"text":"",
"mid":"zrh10vgpx",
"date":"2013-04-09 02:38:52"
},
{
"kids":[],
"uid":"2919315992",
"parent":"zqSyC8fQz",
"text":"",
"mid":"zrgCvnL6o",
"date":"2013-04-09 01:38:31"
},
{
"kids":[],
"uid":"2789818630",
"parent":"zqRo6dvw6",
"text":"",
"mid":"zrgyRkInt",
"date":"2013-04-09 01:29:32"
},
{
"kids":[],
"uid":"2804635134",
"parent":"zqRo6dvw6",
"text":"",
"mid":"zrgyRjnX4",
"date":"2013-04-09 01:29:32"
},
{
"kids":[],
"uid":"hbbbin",
"parent":"",
"text":"",
"mid":"zrfOQFJtI",
"date":"2013-04-08 23:36:09"
},
{
"kids":[],
"uid":"3249132414",
"parent":"zqSBmCVn4",
"text":"回复@杨_xue媛:果断卸载",
"mid":"zrbmhf7QK",
"date":"2013-04-08 12:14:48"
},
{
"kids":[],
"uid":"2919398490",
"parent":"zqSQoip3M",
"text":"",
"mid":"zr90k6tY7",
"date":"2013-04-08 06:15:12"
},
{
"kids":[],
"uid":"1437387794",
"parent":"zqSQoip3M",
"text":"",
"mid":"zr90k5Kak",
"date":"2013-04-08 06:15:13"
},
{
"kids":[],
"uid":"2919614314",
"parent":"zqSyC8fQz",
"text":"",
"mid":"zr8Y5u9tp",
"date":"2013-04-08 06:09:43"
},
{
"kids":[],
"uid":"3043762170",
"parent":"zqSyC8fQz",
"text":"",
"mid":"zr8Y5u9sz",
"date":"2013-04-08 06:09:43"
},
{
"kids":[],
"uid":"2709856012",
"parent":"zqRyIwYCd",
"text":"",
"mid":"zr5VDtuHB",
"date":"2013-04-07 22:25:23"
},
{
"kids":[],
"uid":"1651321105",
"parent":"zqRBwAfur",
"text":"",
"mid":"zr3Ch40cp",
"date":"2013-04-07 16:32:14"
},
{
"kids":[],
"uid":"liangrenzhineng",
"parent":"zqTbzaYrS",
"text":"绝不可能如此收费的。",
"mid":"zr2wO4BoG",
"date":"2013-04-07 13:46:00"
},
{
"kids":[],
"uid":"2383718463",
"parent":"zqRsjpBwX",
"text":"",
"mid":"zr0Oo1ydG",
"date":"2013-04-07 09:23:50"
},
{
"kids":[],
"uid":"2919773100",
"parent":"zqUnv7kbf",
"text":"",
"mid":"zr0J87oN9",
"date":"2013-04-07 09:10:53"
},
{
"kids":[],
"uid":"3043751232",
"parent":"zqUnv7kbf",
"text":"",
"mid":"zr0J87oL0",
"date":"2013-04-07 09:10:53"
},
{
"kids":[],
"uid":"2789753202",
"parent":"",
"text":"",
"mid":"zr0qZbgYm",
"date":"2013-04-07 08:26:11"
},
{
"kids":[],
"uid":"2810714792",
"parent":"",
"text":"",
"mid":"zr0qZalj7",
"date":"2013-04-07 08:26:11"
},
{
"kids":[],
"uid":"2808300612",
"parent":"",
"text":"",
"mid":"zqZAwoADR",
"date":"2013-04-07 06:16:56"
},
{
"kids":[],
"uid":"3043673172",
"parent":"",
"text":"",
"mid":"zqZahoVcd",
"date":"2013-04-07 05:12:17"
},
{
"kids":[],
"uid":"2920283852",
"parent":"zqRpEgP9U",
"text":"",
"mid":"zqY9P0zJv",
"date":"2013-04-07 02:38:24"
},
{
"kids":[],
"uid":"1581691915",
"parent":"",
"text":"",
"mid":"zqXW55GuY",
"date":"2013-04-07 02:04:33"
},
{
"kids":[],
"uid":"2789941730",
"parent":"",
"text":"",
"mid":"zqXW55ptj",
"date":"2013-04-07 02:04:32"
},
{
"kids":[],
"uid":"2994747560",
"parent":"",
"text":"",
"mid":"zqXjudqjC",
"date":"2013-04-07 00:29:28"
},
{
"kids":[],
"uid":"2406655364",
"parent":"zqRzkFw7z",
"text":"",
"mid":"zqWX8lsbM",
"date":"2013-04-06 23:34:24"
},
{
"kids":[],
"uid":"1998393983",
"parent":"zqTgrsdcj",
"text":"这么做无异于釜底抽薪，又不是微信想收费，而是抢了短信和电话的业务被逼收费。要么大家今后都不用移动业务，打电话就用座机，短信用电邮替代，另外多注册腾讯帐号，多点击广告",
"mid":"zqWT1le8q",
"date":"2013-04-06 23:24:14"
},
{
"kids":[],
"uid":"2010112473",
"parent":"zqT7wk4WB",
"text":"不要嘛！陌陌上太害羞啦！",
"mid":"zqWpnFBS4",
"date":"2013-04-06 22:11:15"
},
{
"kids":[],
"uid":"1794270824",
"parent":"",
"text":"",
"mid":"zqWiA08Hb",
"date":"2013-04-06 21:54:26"
},
{
"kids":[],
"uid":"1017020384",
"parent":"",
"text":"如果微信收费了 我就将除了来电显示的其他功能都取消",
"mid":"zqVAPF4Bx",
"date":"2013-04-06 20:06:43"
},
{
"kids":[],
"uid":"2198622861",
"parent":"zqRJgadVi",
"text":"",
"mid":"zqVsL9emO",
"date":"2013-04-06 19:46:49"
},
{
"kids":[],
"uid":"loveiskeer",
"parent":"zqSZLwl8q",
"text":"[生病]",
"mid":"zqUZL39sk",
"date":"2013-04-06 18:35:22"
},
{
"kids":[],
"uid":"frankhellenlee",
"parent":"zqTxeamrU",
"text":"回复@男科医生王古道:[鼓掌]就是木有效率啊",
"mid":"zqUGag5vu",
"date":"2013-04-06 17:47:06"
},
{
"kids":[],
"uid":"2007533421",
"parent":"zqRbX3xHV",
"text":"反对",
"mid":"zqUyommX4",
"date":"2013-04-06 17:27:57"
},
{
"kids":[],
"uid":"1477397170",
"parent":"",
"text":"顶[好棒][好棒]",
"mid":"zqUy0nm9A",
"date":"2013-04-06 17:27:01"
},
{
"kids":[],
"uid":"1406190514",
"parent":"",
"text":"",
"mid":"zqUxk7Zev",
"date":"2013-04-06 17:25:18"
},
{
"kids":[],
"uid":"601296097",
"parent":"",
"text":"顶[好棒][好棒]",
"mid":"zqUxaFhMo",
"date":"2013-04-06 17:24:57"
},
{
"kids":[],
"uid":"dajianzhang",
"parent":"",
"text":"[哼][鄙视]",
"mid":"zqUwAjDR2",
"date":"2013-04-06 17:23:28"
},
{
"kids":[],
"uid":"606360124",
"parent":"",
"text":"顶一顶,继续顶下去",
"mid":"zqUwd00oJ",
"date":"2013-04-06 17:22:32"
},
{
"kids":[],
"uid":"2381809912",
"parent":"",
"text":"顶[好棒][好棒]",
"mid":"zqUvR7SHD",
"date":"2013-04-06 17:21:40"
},
{
"kids":[],
"uid":"2381809912",
"parent":"",
"text":"",
"mid":"zqUvIwz88",
"date":"2013-04-06 17:21:21"
},
{
"kids":[],
"uid":"2745216713",
"parent":"",
"text":"轻轻的,我来了.来为你转转哦",
"mid":"zqUuQahRZ",
"date":"2013-04-06 17:19:12"
},
{
"kids":[],
"uid":"3280577041",
"parent":"",
"text":"坚决反对收费",
"mid":"zqUuKAtC6",
"date":"2013-04-06 17:18:57"
},
{
"kids":[],
"uid":"drwgd",
"parent":"zqTxeamrU",
"text":"回复@李沙显:这样环保。[哈哈]",
"mid":"zqUuysxT1",
"date":"2013-04-06 17:18:29"
},
{
"kids":[],
"uid":"2251264422",
"parent":"",
"text":"[转发]为你转转哦",
"mid":"zqUtxvJTr",
"date":"2013-04-06 17:16:00"
},
{
"kids":[],
"uid":"1642825574",
"parent":"",
"text":"大家都来围观",
"mid":"zqUtgnqzX",
"date":"2013-04-06 17:15:19"
},
{
"kids":[],
"uid":"hepu0217",
"parent":"",
"text":"相互转转吧,支持一哈哈啊",
"mid":"zqUrWeoc5",
"date":"2013-04-06 17:12:01"
},
{
"kids":[],
"uid":"1838156784",
"parent":"",
"text":"转发，增点人气",
"mid":"zqUq4mVc8",
"date":"2013-04-06 17:07:25"
},
{
"kids":[],
"uid":"2843142731",
"parent":"",
"text":"轻轻的,我来了.来为你转转哦",
"mid":"zqUocfW31",
"date":"2013-04-06 17:02:48"
},
{
"kids":[],
"uid":"1991335315",
"parent":"",
"text":"转发，增点人气",
"mid":"zqUo8qoem",
"date":"2013-04-06 17:02:40"
},
{
"kids":[],
"uid":"2385795250",
"parent":"zqU2KwpnT",
"text":"约炮都要收费，太不人道了",
"mid":"zqUo4kmm1",
"date":"2013-04-06 17:02:30"
},
{
"kids":[],
"uid":"1974370777",
"parent":"",
"text":"反对！！！但是有啥用呢？还不照样收！到时轮到新浪了，微博收费也疯狂！",
"mid":"zqUnxetvx",
"date":"2013-04-06 17:01:12"
},
{
"kids":[],
"uid":"1131456577",
"parent":"",
"text":"[围观]支持转发微博",
"mid":"zqUnv8lYx",
"date":"2013-04-06 17:01:07"
},
{
"kids":[
"zr0J87oN9",
"zr0J87oL0"
],
"uid":"2154607794",
"parent":"",
"text":"",
"mid":"zqUnv7kbf",
"date":"2013-04-06 17:01:05"
},
{
"kids":[],
"uid":"2154607794",
"parent":"",
"text":"[浮云][转发]",
"mid":"zqUnojqHv",
"date":"2013-04-06 17:00:49"
},
{
"kids":[],
"uid":"2754580111",
"parent":"",
"text":"",
"mid":"zqUmGAdrG",
"date":"2013-04-06 16:59:06"
},
{
"kids":[],
"uid":"2415115803",
"parent":"",
"text":"朋友就是要相互支持与关注",
"mid":"zqUm2oWvW",
"date":"2013-04-06 16:57:32"
},
{
"kids":[],
"uid":"2824917927",
"parent":"",
"text":"不正当竞争！脑残的垄断企业，脑残的官方机构！还有力撑收费的3个傻冒！如果你是微信用户，大家为了自己的切身利益。快转！严重鄙视这种行为！i[怒][怒][怒][怒][怒][怒][怒]",
"mid":"zqUlGzBg8",
"date":"2013-04-06 16:56:39"
},
{
"kids":[],
"uid":"514564933",
"parent":"",
"text":"努力吧。",
"mid":"zqUixvKOi",
"date":"2013-04-06 16:48:55"
},
{
"kids":[],
"uid":"2369926954",
"parent":"zqTxeamrU",
"text":"",
"mid":"zqUir442L",
"date":"2013-04-06 16:48:38"
},
{
"kids":[],
"uid":"2369926954",
"parent":"zqTxeamrU",
"text":"@齐林在江湖 @千江风月 @cc_蔡苏华 @cc_蔡苏华 @徐春雷Rain",
"mid":"zqUioFVUh",
"date":"2013-04-06 16:48:32"
},
{
"kids":[],
"uid":"3137216043",
"parent":"",
"text":"",
"mid":"zqU5yzIT2",
"date":"2013-04-06 16:16:53"
},
{
"kids":[
"zqUo4kmm1"
],
"uid":"2639832624",
"parent":"",
"text":"朋友就是要相互支持与关注",
"mid":"zqU2KwpnT",
"date":"2013-04-06 16:10:00"
},
{
"kids":[],
"uid":"3258633571",
"parent":"",
"text":"心真黑，",
"mid":"zqTXgrZtx",
"date":"2013-04-06 15:56:29"
},
{
"kids":[],
"uid":"frankhellenlee",
"parent":"zqTxeamrU",
"text":"哈哈，说的也是，以后就写信，养鸽子了[得意地笑]",
"mid":"zqTLT92wf",
"date":"2013-04-06 15:28:26"
},
{
"kids":[],
"uid":"hhnpp",
"parent":"",
"text":"顶！",
"mid":"zqTLDrCne",
"date":"2013-04-06 15:27:48"
},
{
"kids":[],
"uid":"1641413077",
"parent":"",
"text":"说的好，支持[good]",
"mid":"zqTIikvkx",
"date":"2013-04-06 15:19:35"
},
{
"kids":[],
"uid":"3136499865",
"parent":"",
"text":"",
"mid":"zqTH7j4sf",
"date":"2013-04-06 15:16:42"
},
{
"kids":[],
"uid":"1919980517",
"parent":"",
"text":"我靠！流量都不够用，我会乱说么！还要收我话费！",
"mid":"zqTE8ASlx",
"date":"2013-04-06 15:09:22"
},
{
"kids":[],
"uid":"3187852310",
"parent":"",
"text":"",
"mid":"zqTAe2XnT",
"date":"2013-04-06 14:59:42"
},
{
"kids":[
"zqUGag5vu",
"zqUuysxT1",
"zqUir442L",
"zqUioFVUh",
"zqTLT92wf"
],
"uid":"drwgd",
"parent":"zqRJgadVi",
"text":"这样正中电信巨头下怀![哈哈]",
"mid":"zqTxeamrU",
"date":"2013-04-06 14:52:21"
},
{
"kids":[
"zrEPCqrOX",
"zrEPC8QEh"
],
"uid":"3186113252",
"parent":"",
"text":"#热门微博# http:",
"mid":"zqTmzsYuN",
"date":"2013-04-06 14:26:05"
},
{
"kids":[],
"uid":"2421192957",
"parent":"zqTj2vUQg",
"text":"不会吧，真要收费了？",
"mid":"zqTjxxIMi",
"date":"2013-04-06 14:18:35"
},
{
"kids":[
"zqTjxxIMi"
],
"uid":"3066120445",
"parent":"zqT7bij1S",
"text":"以后不用了",
"mid":"zqTj2vUQg",
"date":"2013-04-06 14:17:23"
},
{
"kids":[],
"uid":"1914088582",
"parent":"zqTb7mIbk",
"text":"收费就用别的app呗 又不差它一个。",
"mid":"zqThK97g4",
"date":"2013-04-06 14:14:11"
},
{
"kids":[],
"uid":"nanxiacun",
"parent":"",
"text":"#微信收费# 微信收费了，你还会继续使用吗？ 详情:http:",
"mid":"zqThiB4rx",
"date":"2013-04-06 14:13:04"
},
{
"kids":[],
"uid":"2091689033",
"parent":"",
"text":"虽然不怎么用微信，但是觉得代替短信还是个不错的选择，收费就删除，还有太多软件可以代替了，只要经常聊天的几个人都装一样的就行了",
"mid":"zqThgzKhc",
"date":"2013-04-06 14:12:59"
},
{
"kids":[
"zqWT1le8q"
],
"uid":"1985434361",
"parent":"zqTdDnoBL",
"text":"收费就删，问她老爸去收吧",
"mid":"zqTgrsdcj",
"date":"2013-04-06 14:10:59"
},
{
"kids":[],
"uid":"1851175000",
"parent":"zqSjI7Arx",
"text":"假的吧 那用平板电脑的怎么收费？",
"mid":"zqTfzm3rQ",
"date":"2013-04-06 14:08:49"
},
{
"kids":[],
"uid":"qiuxueqi",
"parent":"",
"text":"分分钟卸载，一直不舍得丢的移动号也可以滚了，还是联通好",
"mid":"zqTfig3Pu",
"date":"2013-04-06 14:08:09"
},
{
"kids":[],
"uid":"willyzm",
"parent":"",
"text":"收就收呗，不用就是了",
"mid":"zqTe2wuOU",
"date":"2013-04-06 14:05:02"
},
{
"kids":[],
"uid":"2760601053",
"parent":"",
"text":"@轩瑷maria @指尖的双生花 @小君子1986 @等房子买车子",
"mid":"zqTdPfPJB",
"date":"2013-04-06 14:04:31"
},
{
"kids":[
"zqTgrsdcj"
],
"uid":"2071772447",
"parent":"zqSZBuRkf",
"text":"啥时候收费啥时候就把微信从手机里删除，永久的那种！支持的转起[offthewall]",
"mid":"zqTdDnoBL",
"date":"2013-04-06 14:04:04"
},
{
"kids":[],
"uid":"2174162084",
"parent":"",
"text":"狗日的运营商，无耻至极！",
"mid":"zqTd88aRS",
"date":"2013-04-06 14:02:47"
},
{
"kids":[],
"uid":"2053699135",
"parent":"zqRbX3xHV",
"text":"好贵啊[泪]",
"mid":"zqTd3FX3Y",
"date":"2013-04-06 14:02:39"
},
{
"kids":[],
"uid":"2985607142",
"parent":"",
"text":"抵制微信收费！转！",
"mid":"zqTcXpCSh",
"date":"2013-04-06 14:02:24"
},
{
"kids":[],
"uid":"1978865671",
"parent":"",
"text":"如果微信按照文字或语音收费？流量是不是免费呢？三大流氓运营商 移动 联通和电信？",
"mid":"zqTceeMDt",
"date":"2013-04-06 14:00:35"
},
{
"kids":[
"zr2wO4BoG"
],
"uid":"lnuonuo",
"parent":"",
"text":"卸载+1[左哼哼]",
"mid":"zqTbzaYrS",
"date":"2013-04-06 13:58:57"
},
{
"kids":[
"zqThK97g4"
],
"uid":"sanji1106",
"parent":"",
"text":"收费就不玩儿了呗",
"mid":"zqTb7mIbk",
"date":"2013-04-06 13:57:51"
},
{
"kids":[],
"uid":"livecome",
"parent":"zqRcxm0BW",
"text":"收费坚决不用！",
"mid":"zqTanynaD",
"date":"2013-04-06 13:56:03"
},
{
"kids":[],
"uid":"1932106405",
"parent":"",
"text":"反对打压！反对垄断！！反对剥削！！",
"mid":"zqTa4ElOX",
"date":"2013-04-06 13:55:18"
},
{
"kids":[],
"uid":"2344592327",
"parent":"",
"text":"",
"mid":"zqT8wB7bi",
"date":"2013-04-06 13:51:30"
},
{
"kids":[
"zqWpnFBS4"
],
"uid":"2563026673",
"parent":"zqRjFpjUp",
"text":"我们一起用陌陌吧[偷笑]",
"mid":"zqT7wk4WB",
"date":"2013-04-06 13:49:00"
},
{
"kids":[],
"uid":"2738602753",
"parent":"",
"text":"一个利益集团断了另一个利益集团的财路.肯定要给政府施加压力的.很正常！应为是在天朝.但我坚决反对双重收费：流量+通话.短信费.  支持的请转发.",
"mid":"zqT7f8SlT",
"date":"2013-04-06 13:48:20"
},
{
"kids":[
"zqTj2vUQg"
],
"uid":"2880764693",
"parent":"",
"text":"",
"mid":"zqT7bij1S",
"date":"2013-04-06 13:48:11"
},
{
"kids":[],
"uid":"1409837182",
"parent":"zqSoGzd46",
"text":"哎，双刃剑啊",
"mid":"zqT728J3c",
"date":"2013-04-06 13:47:47"
},
{
"kids":[],
"uid":"2665847811",
"parent":"zqRbX3xHV",
"text":"",
"mid":"zqT6nmC6d",
"date":"2013-04-06 13:46:11"
},
{
"kids":[],
"uid":"luckywoo",
"parent":"",
"text":"反正类似应用多了是。",
"mid":"zqT50z9yw",
"date":"2013-04-06 13:42:49"
},
{
"kids":[],
"uid":"2704151264",
"parent":"",
"text":"坚决反对双重收费！！！",
"mid":"zqT0PalGV",
"date":"2013-04-06 13:32:29"
},
{
"kids":[
"zqUZL39sk"
],
"uid":"1430706687",
"parent":"",
"text":"国内的三大运营商的用户是要收费了，可是国外的用微信的朋友们，你们怎么收人家的费？又是关起门来欺负自家人了！",
"mid":"zqSZLwl8q",
"date":"2013-04-06 13:29:54"
},
{
"kids":[
"zqTdDnoBL"
],
"uid":"2021547495",
"parent":"",
"text":"[怒][怒]反对！",
"mid":"zqSZBuRkf",
"date":"2013-04-06 13:29:30"
},
{
"kids":[],
"uid":"uxchina",
"parent":"",
"text":"",
"mid":"zqSWBDIbH",
"date":"2013-04-06 13:22:06"
},
{
"kids":[],
"uid":"1831032635",
"parent":"",
"text":"",
"mid":"zqSWast8o",
"date":"2013-04-06 13:21:02"
},
{
"kids":[],
"uid":"1857814535",
"parent":"",
"text":"@Freeman_王 @寻寻觅觅__Xie 看嘛，要收费了。",
"mid":"zqSW842gR",
"date":"2013-04-06 13:20:54"
},
{
"kids":[],
"uid":"1817720977",
"parent":"zqRloEQs5",
"text":"胳膊扭不过大腿的，收费了就不用了呗，继续玩qq，玩微博",
"mid":"zqSUGcSp5",
"date":"2013-04-06 13:17:21"
},
{
"kids":[],
"uid":"1890268947",
"parent":"",
"text":"我去，，，",
"mid":"zqSRRBfu8",
"date":"2013-04-06 13:10:25"
},
{
"kids":[
"zuKVM3bqg",
"zth15nxxm",
"zt73B9eNP",
"zsl8drA2R",
"zsjiHpmIF",
"zsjiH80ZR",
"zriaisqtX",
"zr90k6tY7",
"zr90k5Kak"
],
"uid":"2049747351",
"parent":"",
"text":"在收费前卸了[鄙视][鄙视][鄙视]",
"mid":"zqSQoip3M",
"date":"2013-04-06 13:06:46"
},
{
"kids":[],
"uid":"519753012",
"parent":"",
"text":"Y要这么收我一个月的微信就得小100块，像我这样的人肯定不在少数，到时候肯定闹个天翻地覆，到最后都果断卸载！",
"mid":"zqSOClwCJ",
"date":"2013-04-06 13:02:26"
},
{
"kids":[],
"uid":"1937665374",
"parent":"zqRzkFw7z",
"text":"假的吧",
"mid":"zqSOv0XUi",
"date":"2013-04-06 13:02:08"
},
{
"kids":[],
"uid":"3049045937",
"parent":"zqRbX3xHV",
"text":"反对收费。这样就不用微信了。",
"mid":"zqSOtw4Pc",
"date":"2013-04-06 13:02:05"
},
{
"kids":[],
"uid":"xiaogeqian",
"parent":"",
"text":"",
"mid":"zqSMSdbBA",
"date":"2013-04-06 12:58:08"
},
{
"kids":[],
"uid":"1829341515",
"parent":"zqRbX3xHV",
"text":"真不要脸",
"mid":"zqSJMskGt",
"date":"2013-04-06 12:50:31"
},
{
"kids":[],
"uid":"a237",
"parent":"zqRbX3xHV",
"text":"",
"mid":"zqSJ02bKV",
"date":"2013-04-06 12:48:34"
},
{
"kids":[],
"uid":"2972579372",
"parent":"zqRdxnaVS",
"text":"坚决反对#微信收费#",
"mid":"zqSIoslsV",
"date":"2013-04-06 12:47:06"
},
{
"kids":[],
"uid":"2101407521",
"parent":"",
"text":"",
"mid":"zqSHNfVFk",
"date":"2013-04-06 12:45:36"
},
{
"kids":[],
"uid":"2972918090",
"parent":"",
"text":"反对微信收费，我们用的是我们用钱买回来的流量！超流量，加收费，我用不完的时候，也没见电信移动给我留着！",
"mid":"zqSGzzh6f",
"date":"2013-04-06 12:42:37"
},
{
"kids":[],
"uid":"2040332365",
"parent":"zqRbX3xHV",
"text":"",
"mid":"zqSFheEJv",
"date":"2013-04-06 12:39:25"
},
{
"kids":[],
"uid":"1005514824",
"parent":"",
"text":"一旦收费坚决卸载！",
"mid":"zqSEmbLKr",
"date":"2013-04-06 12:37:08"
},
{
"kids":[],
"uid":"2243876530",
"parent":"zqRzkFw7z",
"text":"能不能解释一下这是怎么回事呢？@评论员杨禹",
"mid":"zqSDz6gwf",
"date":"2013-04-06 12:35:11"
},
{
"kids":[],
"uid":"208363693",
"parent":"",
"text":"[奥特曼]",
"mid":"zqSC7kGbb",
"date":"2013-04-06 12:31:38"
},
{
"kids":[
"zrbmhf7QK"
],
"uid":"3249132414",
"parent":"",
"text":"",
"mid":"zqSBmCVn4",
"date":"2013-04-06 12:29:46"
},
{
"kids":[],
"uid":"1856208402",
"parent":"",
"text":"腾讯CEO马化腾今早已公开澄清微信基础业务不会向用户收费，飞信干不过微信就跟这耍霸道，不革新自己的技术再牛逼的垄断企业也会面临淘汰的危险",
"mid":"zqSBmAJKv",
"date":"2013-04-06 12:29:47"
},
{
"kids":[],
"uid":"1111918821",
"parent":"",
"text":"穷疯了吗，要钱就不用了@棉花糖lucky @筛小筛121 @可乐加冰_84331 @Ss妹儿 @维_愛",
"mid":"zqSAmhGuy",
"date":"2013-04-06 12:27:17"
},
{
"kids":[],
"uid":"yameishop",
"parent":"",
"text":"如果收费，果断不用，没什么大不了，不用不会死。",
"mid":"zqSA86DWB",
"date":"2013-04-06 12:26:43"
},
{
"kids":[],
"uid":"2876418061",
"parent":"",
"text":"#热门微博# http:",
"mid":"zqSzMfxeW",
"date":"2013-04-06 12:25:51"
},
{
"kids":[],
"uid":"1962957645",
"parent":"",
"text":"不用就行了",
"mid":"zqSzhvjJ6",
"date":"2013-04-06 12:24:38"
},
{
"kids":[
"zrgCvnL6o",
"zr8Y5u9tp",
"zr8Y5u9sz"
],
"uid":"1822505765",
"parent":"",
"text":"很多人都在说违背市场就得死，我们看看是谁违背了市场，放眼国外运营商，移动有点不地道吧…@赵小二Bazinga @陈世卿院士 @雷军",
"mid":"zqSyC8fQz",
"date":"2013-04-06 12:22:59"
},
{
"kids":[],
"uid":"2030653955",
"parent":"",
"text":"",
"mid":"zqSy99Qvz",
"date":"2013-04-06 12:21:51"
},
{
"kids":[],
"uid":"2961650684",
"parent":"",
"text":"#热门微博# http:",
"mid":"zqSx5zMiE",
"date":"2013-04-06 12:19:15"
},
{
"kids":[],
"uid":"1962190803",
"parent":"zqRcHlx64",
"text":"",
"mid":"zqSwTpjHS",
"date":"2013-04-06 12:18:46"
},
{
"kids":[],
"uid":"xiaoweivian",
"parent":"",
"text":"黑社会啊！！坚决反对！",
"mid":"zqSwMjORh",
"date":"2013-04-06 12:18:29"
},
{
"kids":[],
"uid":"3226720234",
"parent":"",
"text":"悲哀呀",
"mid":"zqSvH0DQA",
"date":"2013-04-06 12:15:46"
},
{
"kids":[],
"uid":"3117554381",
"parent":"",
"text":"#热门微博# http:",
"mid":"zqSvmjhK0",
"date":"2013-04-06 12:14:59"
},
{
"kids":[],
"uid":"2386482563",
"parent":"zqSsmqemc",
"text":"",
"mid":"zqSuApR51",
"date":"2013-04-06 12:13:04"
},
{
"kids":[],
"uid":"1347640931",
"parent":"zqR89sTLq",
"text":"",
"mid":"zqStN5UlO",
"date":"2013-04-06 12:11:07"
},
{
"kids":[
"zqSuApR51"
],
"uid":"2407062414",
"parent":"",
"text":"垄断企业的无耻行为！愤怒！我很纳闷，为什么你们这些垄断企业日益增长的超高收入依然阻挡不了你们不断下降的道德底限呢！？！请央视炮轰一下中国移动、联通和电信吧，凭什么我们每个月的流量超过包月就要多收钱，而没用完的就清空了不能带到下月使用？现在又在琢磨如何利用微信抽血[怒]",
"mid":"zqSsmqemc",
"date":"2013-04-06 12:07:36"
},
{
"kids":[
"zqT728J3c"
],
"uid":"97118661",
"parent":"",
"text":"@su女 @小僧you礼 @永恒7758 @湮湮小静 @杨小小小乖 @roselzj @哆啦咪法嗦",
"mid":"zqSoGzd46",
"date":"2013-04-06 11:58:32"
},
{
"kids":[],
"uid":"diacenxigirl",
"parent":"",
"text":"果断不用。[哼][哼][哼]鹬蚌相争，受苦滴是老百姓。[怒][怒]期待原始书信传递[爱你][爱你][爱你]",
"mid":"zqSo6giGx",
"date":"2013-04-06 11:57:05"
},
{
"kids":[],
"uid":"1644163367",
"parent":"zqSlZELwv",
"text":"回复@杰克牛在墨尔本:[嘻嘻]",
"mid":"zqSo1xqXK",
"date":"2013-04-06 11:56:55"
},
{
"kids":[],
"uid":"2024400802",
"parent":"zqRf2aCm2",
"text":"微信如收费，俺就用扣扣[哈哈]",
"mid":"zqSmX47Zr",
"date":"2013-04-06 11:54:15"
},
{
"kids":[],
"uid":"1644163367",
"parent":"zqSlZELwv",
"text":"支持你[鼓掌]",
"mid":"zqSmPmXyn",
"date":"2013-04-06 11:53:58"
},
{
"kids":[],
"uid":"2704654324",
"parent":"",
"text":"反对微信收费",
"mid":"zqSmyfz4P",
"date":"2013-04-06 11:53:16"
},
{
"kids":[],
"uid":"1870679734",
"parent":"",
"text":"",
"mid":"zqSmenZ79",
"date":"2013-04-06 11:52:29"
},
{
"kids":[
"zqSo1xqXK",
"zqSmPmXyn"
],
"uid":"1678187842",
"parent":"",
"text":"大家不要担心，微信一收费，我立马开发一个免费的app给大家用，直到工信部找我协商收费问题。杀了一个微信，还有千千万万个app站出来！[奥特曼]",
"mid":"zqSlZELwv",
"date":"2013-04-06 11:51:55"
},
{
"kids":[],
"uid":"2927887847",
"parent":"",
"text":"天朝两大神器＂国际惯例＂＂中国特色＂！！！！！",
"mid":"zqSllcPYR",
"date":"2013-04-06 11:50:18"
},
{
"kids":[
"zrDcn1cyV",
"zqTfzm3rQ"
],
"uid":"shengangbole",
"parent":"",
"text":"",
"mid":"zqSjI7Arx",
"date":"2013-04-06 11:46:17"
},
{
"kids":[],
"uid":"2300561951",
"parent":"zqRbX3xHV",
"text":"他妹，不管卸还是不卸，移动公司是明摆了要抢",
"mid":"zqSjufbxk",
"date":"2013-04-06 11:45:44"
},
{
"kids":[],
"uid":"1219nana",
"parent":"",
"text":"轉發微博",
"mid":"zqSiEuHK9",
"date":"2013-04-06 11:43:41"
},
{
"kids":[],
"uid":"chenhaoxuanange",
"parent":"",
"text":"[鄙视]收费立刻卸载",
"mid":"zqSiA7krR",
"date":"2013-04-06 11:43:30"
},
{
"kids":[],
"uid":"2694687831",
"parent":"",
"text":"抢钞票呀！[鄙視]",
"mid":"zqSijx64a",
"date":"2013-04-06 11:42:50"
},
{
"kids":[],
"uid":"1672128953",
"parent":"zqRbX3xHV",
"text":"",
"mid":"zqSeirtSv",
"date":"2013-04-06 11:32:57"
},
{
"kids":[],
"uid":"vday",
"parent":"zqRbFfbpi",
"text":"反对！",
"mid":"zqSdThxjf",
"date":"2013-04-06 11:31:56"
},
{
"kids":[],
"uid":"2965830961",
"parent":"",
"text":"",
"mid":"zqScJsTsw",
"date":"2013-04-06 11:29:06"
},
{
"kids":[],
"uid":"2512528331",
"parent":"zqRbX3xHV",
"text":"顶起!",
"mid":"zqSceuISZ",
"date":"2013-04-06 11:27:52"
},
{
"kids":[],
"uid":"1373565287",
"parent":"",
"text":"",
"mid":"zqSbos4Fz",
"date":"2013-04-06 11:25:48"
},
{
"kids":[],
"uid":"casatwy",
"parent":"zqRZ6E3Un",
"text":"不收，辟谣了。",
"mid":"zqSbcCnYk",
"date":"2013-04-06 11:25:20"
},
{
"kids":[],
"uid":"kuchikisakura",
"parent":"zqRZ6E3Un",
"text":"我擦，那果断放弃微信。反正同类产品一定会出现的。",
"mid":"zqS9rjGWT",
"date":"2013-04-06 11:20:59"
},
{
"kids":[],
"uid":"3151207557",
"parent":"",
"text":"无耻",
"mid":"zqS8TEFca",
"date":"2013-04-06 11:19:38"
},
{
"kids":[],
"uid":"2187349163",
"parent":"zqR89sTLq",
"text":"",
"mid":"zqS8t54Cm",
"date":"2013-04-06 11:18:34"
},
{
"kids":[],
"uid":"dingfeng0416",
"parent":"zqRQYih2P",
"text":"是的，收费直接卸载……",
"mid":"zqS7jgbzX",
"date":"2013-04-06 11:15:44"
},
{
"kids":[],
"uid":"523670938",
"parent":"zqRbX3xHV",
"text":"改用其他类微信软件吧……大把啦……",
"mid":"zqS6HFHyR",
"date":"2013-04-06 11:14:13"
},
{
"kids":[],
"uid":"1930806197",
"parent":"",
"text":"@碧碧要努力工作 @英琳同学 要收费？",
"mid":"zqS4lqH6w",
"date":"2013-04-06 11:08:25"
},
{
"kids":[],
"uid":"2254823610",
"parent":"",
"text":"反对。",
"mid":"zqS2Qmp5v",
"date":"2013-04-06 11:04:44"
},
{
"kids":[],
"uid":"1869727672",
"parent":"",
"text":"",
"mid":"zqS2GjxZm",
"date":"2013-04-06 11:04:21"
},
{
"kids":[],
"uid":"3242766251",
"parent":"",
"text":"",
"mid":"zqS1d31ea",
"date":"2013-04-06 11:00:42"
},
{
"kids":[],
"uid":"2707031610",
"parent":"zqRQHt1wD",
"text":"[哼]",
"mid":"zqS0H7XfM",
"date":"2013-04-06 10:59:24"
},
{
"kids":[],
"uid":"2954892531",
"parent":"",
"text":"",
"mid":"zqS0230Dl",
"date":"2013-04-06 10:57:48"
},
{
"kids":[],
"uid":"hansoulyoung",
"parent":"",
"text":"房子、車子、票子，壓力山大了。現在還各種瘟疫，肉不能吃，魚不能吃，還有說青菜也不能吃，最後連聊個天都得付費，爺爺的！還能給老百姓一條活路嗎？尊重一下炎黃子孫的生命嗎？[发怒]",
"mid":"zqRZKznCm",
"date":"2013-04-06 10:57:07"
},
{
"kids":[],
"uid":"1420554353",
"parent":"",
"text":"",
"mid":"zqRZJ8qyp",
"date":"2013-04-06 10:57:02"
},
{
"kids":[
"zqSbcCnYk",
"zqS9rjGWT"
],
"uid":"1252243827",
"parent":"zqRMD6vF0",
"text":"不是说不收吗？",
"mid":"zqRZ6E3Un",
"date":"2013-04-06 10:55:31"
},
{
"kids":[],
"uid":"3024924831",
"parent":"zqRXoCdSd",
"text":"垄断，我讨厌垄断！",
"mid":"zqRYSuHEH",
"date":"2013-04-06 10:54:58"
},
{
"kids":[],
"uid":"1192266295",
"parent":"",
"text":"关于微信，谁先收费，我们就放弃这个运营商，转投其他的，另外，我们能不能心齐点，打击打击垄断！腾讯，给力点，我们支持你做中国腾讯通讯，现在腾讯也为难，知道么，我不是任何一方的托，我只是看不惯移动的嘴脸，垄断！所以我们得支持腾讯，谁动腾讯，我们就放弃谁的网络同意的转1",
"mid":"zqRXXbVbY",
"date":"2013-04-06 10:52:41"
},
{
"kids":[
"zqRYSuHEH"
],
"uid":"3167501003",
"parent":"",
"text":"#微信收费# 微信 每条语音1毛（有时候每几秒就是1条语音了），也就是说每几秒或几十秒就要付费1毛！语音对讲发来发去，肯定要发不少吧！还不如 使用 @和悦电话_com @www.heyue.hk，直接打电话，折后 每分钟才几分啊！ 详情:http:",
"mid":"zqRXoCdSd",
"date":"2013-04-06 10:51:19"
},
{
"kids":[],
"uid":"2950011232",
"parent":"zqR89sTLq",
"text":"",
"mid":"zqRX35u88",
"date":"2013-04-06 10:50:27"
},
{
"kids":[],
"uid":"1728368151",
"parent":"",
"text":"6月30坚决卸载了",
"mid":"zqRWDEj0w",
"date":"2013-04-06 10:49:25"
},
{
"kids":[],
"uid":"seanzhang924926",
"parent":"",
"text":"",
"mid":"zqRUPDEY1",
"date":"2013-04-06 10:44:59"
},
{
"kids":[],
"uid":"2669130011",
"parent":"",
"text":"",
"mid":"zqRTIeoxY",
"date":"2013-04-06 10:42:14"
},
{
"kids":[],
"uid":"2482067135",
"parent":"",
"text":"",
"mid":"zqRTt7IWl",
"date":"2013-04-06 10:41:38"
},
{
"kids":[],
"uid":"tongzhanggui",
"parent":"zqR89sTLq",
"text":"如果微信收费，俺就不用了，抵制[怒]",
"mid":"zqRSUhJea",
"date":"2013-04-06 10:40:14"
},
{
"kids":[],
"uid":"zycnuannuan",
"parent":"zqRbX3xHV",
"text":"@feierduo @圆christina @呆萌圓劍媽吳蔚 还真当真了[汗]",
"mid":"zqRRyCCfB",
"date":"2013-04-06 10:36:55"
},
{
"kids":[],
"uid":"1931517182",
"parent":"",
"text":"",
"mid":"zqRRyATn7",
"date":"2013-04-06 10:36:55"
},
{
"kids":[],
"uid":"1989665187",
"parent":"",
"text":"",
"mid":"zqRRvpGDu",
"date":"2013-04-06 10:36:47"
},
{
"kids":[],
"uid":"2971102482",
"parent":"",
"text":"",
"mid":"zqRR0DXVB",
"date":"2013-04-06 10:35:34"
},
{
"kids":[
"zqS7jgbzX"
],
"uid":"1421738790",
"parent":"zqReanAlh",
"text":"收费让鬼用去吧[哼]",
"mid":"zqRQYih2P",
"date":"2013-04-06 10:35:29"
},
{
"kids":[],
"uid":"2443669235",
"parent":"",
"text":"",
"mid":"zqRQQ1Ung",
"date":"2013-04-06 10:35:09"
},
{
"kids":[
"zqS0H7XfM"
],
"uid":"1910775610",
"parent":"zqR8bfnKa",
"text":"",
"mid":"zqRQHt1wD",
"date":"2013-04-06 10:34:48"
},
{
"kids":[],
"uid":"2319839610",
"parent":"zqR8bfnKa",
"text":"[怒]",
"mid":"zqROUlyVw",
"date":"2013-04-06 10:30:24"
},
{
"kids":[],
"uid":"2129259765",
"parent":"",
"text":"赶快用！最后的疯狂！@快到锅里来212 @就叫白桦树 @非常正常人 @可可026 @大龄吃货毛毛 @振华李",
"mid":"zqROqey9h",
"date":"2013-04-06 10:29:12"
},
{
"kids":[],
"uid":"huachun1203",
"parent":"",
"text":"[弱][弱]",
"mid":"zqROl9ZHV",
"date":"2013-04-06 10:29:00"
},
{
"kids":[],
"uid":"mingig",
"parent":"",
"text":"反对收费",
"mid":"zqRNBDVxv",
"date":"2013-04-06 10:27:12"
},
{
"kids":[],
"uid":"sam2005",
"parent":"zqRzkFw7z",
"text":"",
"mid":"zqRNcwSyx",
"date":"2013-04-06 10:26:12"
},
{
"kids":[],
"uid":"1402083274",
"parent":"",
"text":"",
"mid":"zqRMOiova",
"date":"2013-04-06 10:25:13"
},
{
"kids":[
"zqRZ6E3Un"
],
"uid":"casatwy",
"parent":"zqRHegV8P",
"text":"真要收费了？果然我还是低估了那帮混蛋的道德水平么~",
"mid":"zqRMD6vF0",
"date":"2013-04-06 10:24:47"
},
{
"kids":[],
"uid":"2740761330",
"parent":"zqRbX3xHV",
"text":"准备不用[怒]",
"mid":"zqRLUbq3X",
"date":"2013-04-06 10:23:00"
},
{
"kids":[],
"uid":"1820484135",
"parent":"",
"text":"反对收费!若收费，坚决御载!",
"mid":"zqRLwx9Fx",
"date":"2013-04-06 10:22:04"
},
{
"kids":[
"zqVsL9emO",
"zqTxeamrU"
],
"uid":"1963101065",
"parent":"zqRzkFw7z",
"text":"只要收费马上删除微信！",
"mid":"zqRJgadVi",
"date":"2013-04-06 10:16:29"
},
{
"kids":[],
"uid":"nini722",
"parent":"",
"text":"双重收费！你妹啊！",
"mid":"zqRIU1dze",
"date":"2013-04-06 10:15:36"
},
{
"kids":[],
"uid":"2497286213",
"parent":"zqRzkFw7z",
"text":"",
"mid":"zqRIqrXGe",
"date":"2013-04-06 10:14:25"
},
{
"kids":[],
"uid":"2681766404",
"parent":"",
"text":"一个微信倒下，千万个微信站起来",
"mid":"zqRIkwA8z",
"date":"2013-04-06 10:14:12"
},
{
"kids":[
"zqRMD6vF0"
],
"uid":"congguiming",
"parent":"zqRGFqZbI",
"text":"不只是跟不上时代，简直是有碍时代进步……",
"mid":"zqRHegV8P",
"date":"2013-04-06 10:11:30"
},
{
"kids":[],
"uid":"1838160102",
"parent":"",
"text":"转发",
"mid":"zqRHcgUMn",
"date":"2013-04-06 10:11:23"
},
{
"kids":[],
"uid":"1876371155",
"parent":"",
"text":"收费收费收费！破ZF！以后是不是从出门开始的每走一步都要计费[怒][汗]",
"mid":"zqRH9yXc3",
"date":"2013-04-06 10:11:18"
},
{
"kids":[
"zqRHegV8P"
],
"uid":"congguiming",
"parent":"",
"text":"真搞笑……一个微信倒下去，100个微信站起来。这些个跟不上时代的巨头早晚被阉割掉……",
"mid":"zqRGFqZbI",
"date":"2013-04-06 10:10:06"
},
{
"kids":[],
"uid":"1867033290",
"parent":"zqRkpuAnR",
"text":"垄断本来就会阻碍行业的发展",
"mid":"zqRGvnFZ3",
"date":"2013-04-06 10:09:42"
},
{
"kids":[],
"uid":"yourgraceleo",
"parent":"",
"text":"免费通讯工具何其多？靠这样堵怎么堵的住？",
"mid":"zqRGptt2C",
"date":"2013-04-06 10:09:28"
},
{
"kids":[],
"uid":"yourfamilydoctor",
"parent":"zqRbX3xHV",
"text":"看着很扯，一想国情，豁然开朗。[右哼哼]",
"mid":"zqRFOwFSd",
"date":"2013-04-06 10:08:00"
},
{
"kids":[],
"uid":"2104579221",
"parent":"",
"text":"#热门微博# http:",
"mid":"zqRFN5ER0",
"date":"2013-04-06 10:07:56"
},
{
"kids":[],
"uid":"stillremains",
"parent":"",
"text":"[吃惊] 不是吧",
"mid":"zqRFKpVif",
"date":"2013-04-06 10:07:50"
},
{
"kids":[
"zrmTKvZaU"
],
"uid":"1415473812",
"parent":"zqRbX3xHV",
"text":"",
"mid":"zqRDUkxEo",
"date":"2013-04-06 10:03:18"
},
{
"kids":[],
"uid":"1650350892",
"parent":"zqRydwrBu",
"text":"",
"mid":"zqRDLsz5c",
"date":"2013-04-06 10:02:57"
},
{
"kids":[],
"uid":"2146749362",
"parent":"",
"text":"怪异",
"mid":"zqRDjnpmn",
"date":"2013-04-06 10:01:51"
},
{
"kids":[],
"uid":"2772838911",
"parent":"zqRbX3xHV",
"text":"擦，我国真是与众不同啊，果然是社会主义特色",
"mid":"zqRCLa80E",
"date":"2013-04-06 10:00:28"
},
{
"kids":[],
"uid":"322850202",
"parent":"zqRzkFw7z",
"text":"收费的那一天我就不用微信了",
"mid":"zqRCC0wfq",
"date":"2013-04-06 10:00:05"
},
{
"kids":[],
"uid":"2081252153",
"parent":"zqRi17Jss",
"text":"",
"mid":"zqRCvucX2",
"date":"2013-04-06 09:59:51"
},
{
"kids":[],
"uid":"1948425877",
"parent":"",
"text":"",
"mid":"zqRCo75Q0",
"date":"2013-04-06 09:59:32"
},
{
"kids":[],
"uid":"1039114630",
"parent":"zqRzfl9C7",
"text":"",
"mid":"zqRBTlBW4",
"date":"2013-04-06 09:58:19"
},
{
"kids":[
"zr3Ch40cp"
],
"uid":"2466571713",
"parent":"zqRyIwYCd",
"text":"离了微信照样活！",
"mid":"zqRBwAfur",
"date":"2013-04-06 09:57:25"
},
{
"kids":[],
"uid":"1967751055",
"parent":"",
"text":"",
"mid":"zqRBeh5WJ",
"date":"2013-04-06 09:56:42"
},
{
"kids":[],
"uid":"3221360503",
"parent":"zqRbX3xHV",
"text":"靠，这就是热议结果？",
"mid":"zqRA5lJ69",
"date":"2013-04-06 09:53:53"
},
{
"kids":[],
"uid":"2608399147",
"parent":"zqRu6fAO2",
"text":"那就不用了呗，不要钱我才来用一下的",
"mid":"zqRzRupAT",
"date":"2013-04-06 09:53:19"
},
{
"kids":[
"zqWX8lsbM",
"zqSOv0XUi",
"zqSDz6gwf",
"zqRNcwSyx",
"zqRJgadVi",
"zqRIqrXGe",
"zqRCC0wfq"
],
"uid":"drwgd",
"parent":"",
"text":"支持庄哥![话筒]",
"mid":"zqRzkFw7z",
"date":"2013-04-06 09:52:01"
},
{
"kids":[
"zqRBTlBW4"
],
"uid":"1673704895",
"parent":"zqR89sTLq",
"text":"",
"mid":"zqRzfl9C7",
"date":"2013-04-06 09:51:49"
},
{
"kids":[],
"uid":"2865168810",
"parent":"zqR89sTLq",
"text":"强烈反对，太坑人了。",
"mid":"zqRz9qvgO",
"date":"2013-04-06 09:51:35"
},
{
"kids":[
"zr5VDtuHB",
"zqRBwAfur"
],
"uid":"2498576185",
"parent":"zqRbX3xHV",
"text":"要和微信说拜拜了[挖鼻屎][挖鼻屎]",
"mid":"zqRyIwYCd",
"date":"2013-04-06 09:50:31"
},
{
"kids":[],
"uid":"1788845877",
"parent":"zqRbX3xHV",
"text":"收费就坚决不用！",
"mid":"zqRyCFiho",
"date":"2013-04-06 09:50:17"
},
{
"kids":[],
"uid":"1734817937",
"parent":"",
"text":"如果是真的，明年6月30号就是微信的忌日",
"mid":"zqRyqymjh",
"date":"2013-04-06 09:49:47"
},
{
"kids":[
"zqRDLsz5c"
],
"uid":"songkaicheng",
"parent":"zqR7DxYOZ",
"text":"",
"mid":"zqRydwrBu",
"date":"2013-04-06 09:49:18"
},
{
"kids":[],
"uid":"aralemxj",
"parent":"zqRbX3xHV",
"text":"国外发展吧",
"mid":"zqRxkwwSf",
"date":"2013-04-06 09:47:06"
},
{
"kids":[],
"uid":"renjiananqi",
"parent":"zqR89sTLq",
"text":"已不用微信很多年。但必须反对双重收费！",
"mid":"zqRwZxEfu",
"date":"2013-04-06 09:46:15"
},
{
"kids":[],
"uid":"1867498291",
"parent":"zqRsz5vNc",
"text":"",
"mid":"zqRuTzTNB",
"date":"2013-04-06 09:41:06"
},
{
"kids":[],
"uid":"2646670640",
"parent":"zqR89sTLq",
"text":"不该收费",
"mid":"zqRunClWN",
"date":"2013-04-06 09:39:50"
},
{
"kids":[],
"uid":"1913705345",
"parent":"zqR89sTLq",
"text":"可恶[怒]",
"mid":"zqRu8251u",
"date":"2013-04-06 09:39:11"
},
{
"kids":[
"zqRzRupAT"
],
"uid":"1912458121",
"parent":"zqRbX3xHV",
"text":"这么多聊天工具，为什么要用收费的呢？喜欢收就收吧，觉得不合算用别的阿，反正也没人革命的",
"mid":"zqRu6fAO2",
"date":"2013-04-06 09:39:07"
},
{
"kids":[],
"uid":"2399091933",
"parent":"zqRbFfbpi",
"text":"",
"mid":"zqRu5ANAg",
"date":"2013-04-06 09:39:07"
},
{
"kids":[],
"uid":"1660070595",
"parent":"zqRnc45Ss",
"text":"反对",
"mid":"zqRtFDBfJ",
"date":"2013-04-06 09:38:04"
},
{
"kids":[
"zqRuTzTNB"
],
"uid":"koza",
"parent":"",
"text":"虽然不用微信，但强烈反对微信收费。",
"mid":"zqRsz5vNc",
"date":"2013-04-06 09:35:21"
},
{
"kids":[
"zr0Oo1ydG"
],
"uid":"2282806810",
"parent":"",
"text":"",
"mid":"zqRsjpBwX",
"date":"2013-04-06 09:34:44"
},
{
"kids":[],
"uid":"1886383013",
"parent":"zqRbX3xHV",
"text":"让人失望了。",
"mid":"zqRsj9MKW",
"date":"2013-04-06 09:34:43"
},
{
"kids":[],
"uid":"1151104015",
"parent":"",
"text":"@翅膀不能飞 @婉卿佳人 @高晓松 @NBTV看看看",
"mid":"zqRsgq3pG",
"date":"2013-04-06 09:34:37"
},
{
"kids":[],
"uid":"2142233393",
"parent":"zqR89sTLq",
"text":"",
"mid":"zqRs5cowj",
"date":"2013-04-06 09:34:10"
},
{
"kids":[],
"uid":"gutousama",
"parent":"zqRnc45Ss",
"text":"机场新闻里面刚刚马化腾还在说微信收费是谣言呢[思考]运营商的基站维护每年确实需要非常的钱，但现在成本已经压很低了。利润啥的大部分进了谁的腰包嘛。",
"mid":"zqRrP0zRA",
"date":"2013-04-06 09:33:31"
},
{
"kids":[],
"uid":"2624369454",
"parent":"",
"text":"",
"mid":"zqRrBoL9X",
"date":"2013-04-06 09:32:58"
},
{
"kids":[],
"uid":"3265139744",
"parent":"",
"text":"[织]",
"mid":"zqRrzkFLg",
"date":"2013-04-06 09:32:54"
},
{
"kids":[],
"uid":"1607403747",
"parent":"zqRnMpqGZ",
"text":"反对反对！流量也要钱啊~@_____Q______ @leedy_zhao @vivian1022 @咖啡色蓝格子",
"mid":"zqRrmCN2t",
"date":"2013-04-06 09:32:24"
},
{
"kids":[],
"uid":"1445639721",
"parent":"",
"text":"",
"mid":"zqRr8rLTR",
"date":"2013-04-06 09:31:50"
},
{
"kids":[],
"uid":"1878996914",
"parent":"",
"text":"一个很坏的示范！这不是转用whatsapp就能解决的问题！",
"mid":"zqRr13Yd6",
"date":"2013-04-06 09:31:31"
},
{
"kids":[],
"uid":"1646277433",
"parent":"",
"text":"",
"mid":"zqRqPcCUD",
"date":"2013-04-06 09:31:04"
},
{
"kids":[
"zrh10vgpx"
],
"uid":"2258204723",
"parent":"zqRp2pm2S",
"text":"",
"mid":"zqRqhx8C1",
"date":"2013-04-06 09:29:43"
},
{
"kids":[
"zs1okyjve",
"zrWOB2pu8",
"zrWOB2prX",
"zqY9P0zJv"
],
"uid":"2579740173",
"parent":"zqRbX3xHV",
"text":"雅蠛蝶！！！",
"mid":"zqRpEgP9U",
"date":"2013-04-06 09:28:08"
},
{
"kids":[],
"uid":"1619480817",
"parent":"zqRbFfbpi",
"text":"",
"mid":"zqRpoxiom",
"date":"2013-04-06 09:27:33"
},
{
"kids":[],
"uid":"1662013103",
"parent":"zqRbX3xHV",
"text":"流量不是钱么。。。为毛还收费。。。@苏西黑妥耶夫斯基 。。。以后打发无聊还要用钱。。。",
"mid":"zqRp5Dsqo",
"date":"2013-04-06 09:26:48"
},
{
"kids":[
"zqRqhx8C1"
],
"uid":"1412234843",
"parent":"zqRm4jYPN",
"text":"工信部真垃圾",
"mid":"zqRp2pm2S",
"date":"2013-04-06 09:26:40"
},
{
"kids":[],
"uid":"2140361195",
"parent":"",
"text":"哈哈，我用微博",
"mid":"zqRogvary",
"date":"2013-04-06 09:24:46"
},
{
"kids":[],
"uid":"1823259592",
"parent":"zqRm4jYPN",
"text":"如果真的收费，无论选择短信还是微信，消费者都是大头。[泪]",
"mid":"zqRo80HSt",
"date":"2013-04-06 09:24:25"
},
{
"kids":[
"zrqVSwoX4",
"zrgyRkInt",
"zrgyRjnX4"
],
"uid":"2449850444",
"parent":"zqRbX3xHV",
"text":"",
"mid":"zqRo6dvw6",
"date":"2013-04-06 09:24:21"
},
{
"kids":[],
"uid":"2552496451",
"parent":"zqRbX3xHV",
"text":"我,不发微信了",
"mid":"zqRo4rJui",
"date":"2013-04-06 09:24:16"
},
{
"kids":[],
"uid":"2399386413",
"parent":"",
"text":"",
"mid":"zqRnUE1ml",
"date":"2013-04-06 09:23:54"
},
{
"kids":[
"zqRrmCN2t"
],
"uid":"2931813531",
"parent":"",
"text":"虽然用得不多，还是坚决反对！割韭菜也没这种割法。",
"mid":"zqRnMpqGZ",
"date":"2013-04-06 09:23:33"
},
{
"kids":[],
"uid":"2270188512",
"parent":"",
"text":"[衰]",
"mid":"zqRnhoo8T",
"date":"2013-04-06 09:22:19"
},
{
"kids":[
"zqRtFDBfJ",
"zqRrP0zRA"
],
"uid":"janefly819",
"parent":"zqRbX3xHV",
"text":"微信你好 微信再见",
"mid":"zqRnc45Ss",
"date":"2013-04-06 09:22:06"
},
{
"kids":[],
"uid":"2166855905",
"parent":"zqRbX3xHV",
"text":"不会吧，那以后的套餐里是不是也要包含几百条微信",
"mid":"zqRmCzdiO",
"date":"2013-04-06 09:20:43"
},
{
"kids":[],
"uid":"2480590413",
"parent":"",
"text":"真可笑",
"mid":"zqRmAdwRW",
"date":"2013-04-06 09:20:37"
},
{
"kids":[],
"uid":"3185288960",
"parent":"",
"text":"切……",
"mid":"zqRmvwZaL",
"date":"2013-04-06 09:20:26"
},
{
"kids":[
"zqRp2pm2S",
"zqRo80HSt"
],
"uid":"hujianhua999",
"parent":"zqRftlJvZ",
"text":"真相？",
"mid":"zqRm4jYPN",
"date":"2013-04-06 09:19:21"
},
{
"kids":[
"zqSUGcSp5"
],
"uid":"wangyun9420",
"parent":"zqR89sTLq",
"text":"@刺猬zl0 @Julia-zx @汐汐新娘造型工作室 我们也给转起吧！！",
"mid":"zqRloEQs5",
"date":"2013-04-06 09:17:41"
},
{
"kids":[],
"uid":"1635155741",
"parent":"zqRbX3xHV",
"text":"求辟谣！",
"mid":"zqRkUfsUj",
"date":"2013-04-06 09:16:29"
},
{
"kids":[],
"uid":"2833108352",
"parent":"zqR89sTLq",
"text":"",
"mid":"zqRkI5u1i",
"date":"2013-04-06 09:16:00"
},
{
"kids":[],
"uid":"2043859745",
"parent":"zqRbFfbpi",
"text":"",
"mid":"zqRkFsOnN",
"date":"2013-04-06 09:15:53"
},
{
"kids":[],
"uid":"2391465414",
"parent":"",
"text":"强烈反对",
"mid":"zqRks91Kf",
"date":"2013-04-06 09:15:22"
},
{
"kids":[
"zqRGvnFZ3"
],
"uid":"2601773097",
"parent":"zqRbX3xHV",
"text":"[衰]",
"mid":"zqRkpuAnR",
"date":"2013-04-06 09:15:15"
},
{
"kids":[],
"uid":"2239125582",
"parent":"zqRbX3xHV",
"text":"这不允许[抓狂][抓狂][抓狂][哼][哼][哼]",
"mid":"zqRkn9D1k",
"date":"2013-04-06 09:15:09"
},
{
"kids":[],
"uid":"1419550872",
"parent":"zqRbX3xHV",
"text":"7月1日起停用微信!",
"mid":"zqRkezeQu",
"date":"2013-04-06 09:14:49"
},
{
"kids":[],
"uid":"208585727",
"parent":"zqR89sTLq",
"text":"米聊的春天就要来了@雷军 @黎万强",
"mid":"zqRkbhjbj",
"date":"2013-04-06 09:14:42"
},
{
"kids":[
"zqT7wk4WB"
],
"uid":"2010112473",
"parent":"",
"text":"真的假的？",
"mid":"zqRjFpjUp",
"date":"2013-04-06 09:13:26"
},
{
"kids":[],
"uid":"2085301021",
"parent":"zqRbX3xHV",
"text":"",
"mid":"zqRjtzgic",
"date":"2013-04-06 09:12:58"
},
{
"kids":[],
"uid":"2827394397",
"parent":"",
"text":"强烈抗议！",
"mid":"zqRi6aaWg",
"date":"2013-04-06 09:09:34"
},
{
"kids":[],
"uid":"2684508584",
"parent":"",
"text":"不会吧@well-beingcx",
"mid":"zqRi4EfXS",
"date":"2013-04-06 09:09:31"
},
{
"kids":[
"zqRCvucX2"
],
"uid":"2427929950",
"parent":"zqR89sTLq",
"text":"收费的话估计就没什么人玩了",
"mid":"zqRi17Jss",
"date":"2013-04-06 09:09:22"
},
{
"kids":[],
"uid":"1923573497",
"parent":"",
"text":"坚决抵制垄断，要平等竞争，要自由发展，要和谐正能量",
"mid":"zqRhQth72",
"date":"2013-04-06 09:08:57"
},
{
"kids":[],
"uid":"1046799661",
"parent":"zqR89sTLq",
"text":"",
"mid":"zqRho9sci",
"date":"2013-04-06 09:07:49"
},
{
"kids":[],
"uid":"2031304905",
"parent":"zqRbX3xHV",
"text":"",
"mid":"zqRh68Lu6",
"date":"2013-04-06 09:07:05"
},
{
"kids":[],
"uid":"2280243020",
"parent":"",
"text":"",
"mid":"zqRgWFSZc",
"date":"2013-04-06 09:06:44"
},
{
"kids":[],
"uid":"3279855171",
"parent":"zqR89sTLq",
"text":"我和身边的朋友都一致说微信收费就卸载，不用了，那么多可以一样免费沟通的软件呢，对做出收费机构的机构极度失望。中国是抢钱想疯了吗！",
"mid":"zqRgO6mI9",
"date":"2013-04-06 09:06:22"
},
{
"kids":[],
"uid":"3046729707",
"parent":"",
"text":"",
"mid":"zqRgNd7JS",
"date":"2013-04-06 09:06:21"
},
{
"kids":[],
"uid":"2696536673",
"parent":"zqR89sTLq",
"text":"",
"mid":"zqRgeDYDL",
"date":"2013-04-06 09:04:59"
},
{
"kids":[
"zqRm4jYPN"
],
"uid":"1632114552",
"parent":"",
"text":"流量已经收费了的，还要收？",
"mid":"zqRftlJvZ",
"date":"2013-04-06 09:03:06"
},
{
"kids":[],
"uid":"2659785523",
"parent":"zqR89sTLq",
"text":"",
"mid":"zqRf6AnNb",
"date":"2013-04-06 09:02:12"
},
{
"kids":[
"zqSmX47Zr"
],
"uid":"2764468897",
"parent":"zqRbX3xHV",
"text":"微信收费的那天也就是微信出局的那天",
"mid":"zqRf2aCm2",
"date":"2013-04-06 09:02:01"
},
{
"kids":[],
"uid":"2193390961",
"parent":"zqR89sTLq",
"text":"最多以后不玩微信，系中国咩都讲钱",
"mid":"zqRervTcL",
"date":"2013-04-06 09:00:34"
},
{
"kids":[],
"uid":"7lost",
"parent":"zqRbFfbpi",
"text":"微信都收费了，QQ聊天GF也是要收费的",
"mid":"zqRelm0Yj",
"date":"2013-04-06 09:00:18"
},
{
"kids":[],
"uid":"1823222327",
"parent":"zqRbX3xHV",
"text":"",
"mid":"zqRek7IYg",
"date":"2013-04-06 09:00:16"
},
{
"kids":[
"zqRQYih2P"
],
"uid":"dingfeng0416",
"parent":"zqRbX3xHV",
"text":"穷疯了……蛋疼！",
"mid":"zqReanAlh",
"date":"2013-04-06 08:59:52"
},
{
"kids":[],
"uid":"1849299512",
"parent":"zqRbX3xHV",
"text":"要撤咯",
"mid":"zqRe5l6l7",
"date":"2013-04-06 08:59:41"
},
{
"kids":[],
"uid":"630411233",
"parent":"zqRbX3xHV",
"text":"为毛收费，收费集体抗议不用……大不了玩QQ啊，扣扣也可以发语音",
"mid":"zqRdLzHC0",
"date":"2013-04-06 08:58:54"
},
{
"kids":[
"zqSIoslsV"
],
"uid":"2209588955",
"parent":"",
"text":"坚决反对#微信收费#!流量已经收费!再收费就坚决卸载!",
"mid":"zqRdxnaVS",
"date":"2013-04-06 08:58:20"
},
{
"kids":[],
"uid":"2198958931",
"parent":"zqRbX3xHV",
"text":"用到流量已经让人很头疼了@半个耳洞 @猫九-99 @大宝贝222 @年少疯狂盲从李宇春 @绽放的树叶不是花",
"mid":"zqRdn1FYd",
"date":"2013-04-06 08:57:54"
},
{
"kids":[],
"uid":"215977013",
"parent":"zqRbX3xHV",
"text":"反对反对",
"mid":"zqRd4oulF",
"date":"2013-04-06 08:57:10"
},
{
"kids":[],
"uid":"2963170755",
"parent":"zqRbX3xHV",
"text":"",
"mid":"zqRcZn51a",
"date":"2013-04-06 08:56:58"
},
{
"kids":[
"zqSwTpjHS"
],
"uid":"1647964931",
"parent":"zqRbX3xHV",
"text":"",
"mid":"zqRcHlx64",
"date":"2013-04-06 08:56:16"
},
{
"kids":[],
"uid":"1731946032",
"parent":"",
"text":"顶……",
"mid":"zqRcA1JHs",
"date":"2013-04-06 08:55:57"
},
{
"kids":[
"zqTanynaD"
],
"uid":"2177059831",
"parent":"zqR89sTLq",
"text":"",
"mid":"zqRcxm0BW",
"date":"2013-04-06 08:55:51"
},
{
"kids":[],
"uid":"badgui",
"parent":"",
"text":"也许以后我也不会再用了！QQ什么都可以办到！何必花那个钱！！没有QQ的快点注册吧",
"mid":"zqRcigZS8",
"date":"2013-04-06 08:55:15"
},
{
"kids":[
"zqUyommX4",
"zqTd3FX3Y",
"zqT6nmC6d",
"zqSOtw4Pc",
"zqSJMskGt",
"zqSJ02bKV",
"zqSFheEJv",
"zqSjufbxk",
"zqSeirtSv",
"zqSceuISZ",
"zqS6HFHyR",
"zqRRyCCfB",
"zqRLUbq3X",
"zqRFOwFSd",
"zqRDUkxEo",
"zqRCLa80E",
"zqRA5lJ69",
"zqRyIwYCd",
"zqRyCFiho",
"zqRxkwwSf",
"zqRu6fAO2",
"zqRsj9MKW",
"zqRpEgP9U",
"zqRp5Dsqo",
"zqRo6dvw6",
"zqRo4rJui",
"zqRnc45Ss",
"zqRmCzdiO",
"zqRkUfsUj",
"zqRkpuAnR",
"zqRkn9D1k",
"zqRkezeQu",
"zqRjtzgic",
"zqRh68Lu6",
"zqRf2aCm2",
"zqRek7IYg",
"zqReanAlh",
"zqRe5l6l7",
"zqRdLzHC0",
"zqRdn1FYd",
"zqRd4oulF",
"zqRcZn51a",
"zqRcHlx64"
],
"uid":"yiyuannadianshi",
"parent":"zqRapftld",
"text":"蛋蛋有点疼[泪]",
"mid":"zqRbX3xHV",
"date":"2013-04-06 08:54:24"
},
{
"kids":[],
"uid":"2024921451",
"parent":"zqR89sTLq",
"text":"没有微信还有QQ，有新浪呢，怕啥",
"mid":"zqRbOrYZO",
"date":"2013-04-06 08:54:04"
},
{
"kids":[],
"uid":"2310063517",
"parent":"zqR89sTLq",
"text":"@官月月的幸福生活 @导航Q @冬瓜梨 @大展红-途 @niaoer的幸福 @爱芝士的敏敏 @BP王子 @夏日里的影子",
"mid":"zqRbJ6QNQ",
"date":"2013-04-06 08:53:52"
},
{
"kids":[
"zqSdThxjf",
"zqRu5ANAg",
"zqRpoxiom",
"zqRkFsOnN",
"zqRelm0Yj"
],
"uid":"yt7501133",
"parent":"",
"text":"",
"mid":"zqRbFfbpi",
"date":"2013-04-06 08:53:43"
},
{
"kids":[],
"uid":"1858723051",
"parent":"",
"text":"#微信收费# 转发微博 话题详情:http:",
"mid":"zqRbAwIdT",
"date":"2013-04-06 08:53:32"
},
{
"kids":[],
"uid":"2310063517",
"parent":"zqR89sTLq",
"text":"",
"mid":"zqRb6oelj",
"date":"2013-04-06 08:52:20"
},
{
"kids":[
"zqRbX3xHV"
],
"uid":"tisc",
"parent":"zqR89sTLq",
"text":"最近，我朝总是出现光怪陆离的现场！",
"mid":"zqRapftld",
"date":"2013-04-06 08:50:37"
},
{
"kids":[],
"uid":"3202617120",
"parent":"",
"text":"必须反对啊，二次交钱啊！！！！！#请插入话题名称#微信收费#@左小祖咒 @穿NIKE的渔夫 @李开复 @薛蛮子",
"mid":"zqRakwScz",
"date":"2013-04-06 08:50:25"
},
{
"kids":[],
"uid":"1446202850",
"parent":"",
"text":"",
"mid":"zqR9WztEv",
"date":"2013-04-06 08:49:29"
},
{
"kids":[],
"uid":"1915406535",
"parent":"zqR89sTLq",
"text":"转起来，让大家一起鄙视他们",
"mid":"zqR9kcBuu",
"date":"2013-04-06 08:47:57"
},
{
"kids":[],
"uid":"sbrenddie",
"parent":"zqR89sTLq",
"text":"那去了国外这微信费怎么收？",
"mid":"zqR9f8b8s",
"date":"2013-04-06 08:47:45"
},
{
"kids":[],
"uid":"1266217932",
"parent":"",
"text":"。。。还可以这样哦。。。",
"mid":"zqR8pazJ7",
"date":"2013-04-06 08:45:41"
},
{
"kids":[],
"uid":"3097267664",
"parent":"",
"text":"",
"mid":"zqR8k9a6V",
"date":"2013-04-06 08:45:29"
},
{
"kids":[
"zqRQHt1wD",
"zqROUlyVw"
],
"uid":"2459098751",
"parent":"",
"text":"反对[抓狂]",
"mid":"zqR8bfnKa",
"date":"2013-04-06 08:45:08"
},
{
"kids":[
"zqStN5UlO",
"zqS8t54Cm",
"zqRX35u88",
"zqRSUhJea",
"zqRzfl9C7",
"zqRz9qvgO",
"zqRwZxEfu",
"zqRunClWN",
"zqRu8251u",
"zqRs5cowj",
"zqRloEQs5",
"zqRkI5u1i",
"zqRkbhjbj",
"zqRi17Jss",
"zqRho9sci",
"zqRgO6mI9",
"zqRgeDYDL",
"zqRf6AnNb",
"zqRervTcL",
"zqRcxm0BW",
"zqRbOrYZO",
"zqRbJ6QNQ",
"zqRb6oelj",
"zqRapftld",
"zqR9kcBuu",
"zqR9f8b8s"
],
"uid":"1435723965",
"parent":"",
"text":"让人失望了。",
"mid":"zqR89sTLq",
"date":"2013-04-06 08:45:03"
},
{
"kids":[],
"uid":"1659274522",
"parent":"",
"text":"找个替代软件吧",
"mid":"zqR854VgZ",
"date":"2013-04-06 08:44:52"
},
{
"kids":[],
"uid":"2184357043",
"parent":"",
"text":"[怒][怒][怒][怒]",
"mid":"zqR81vaBR",
"date":"2013-04-06 08:44:45"
},
{
"kids":[],
"uid":"my512",
"parent":"",
"text":"",
"mid":"zqR7MpX0I",
"date":"2013-04-06 08:44:09"
},
{
"kids":[
"zqRydwrBu"
],
"uid":"1915546641",
"parent":"",
"text":"",
"mid":"zqR7DxYOZ",
"date":"2013-04-06 08:43:48"
},
{
"kids":[],
"uid":"52466246",
"parent":"",
"text":"",
"mid":"zqR7i0QWv",
"date":"2013-04-06 08:42:55"
}
]